README.md
setup.py
2.5D.egg-info/PKG-INFO
2.5D.egg-info/SOURCES.txt
2.5D.egg-info/dependency_links.txt
2.5D.egg-info/top_level.txt
d25/__init__.py