Metadata-Version: 2.1
Name: 2.5D
Version: 0.0.1
Summary: With this module you can create kind of 3D games easily.
Home-page: http://k6nesoftware.com
Author: K6nE
Author-email: maknix@k6nesoftware.com
License: UNKNOWN
Platform: UNKNOWN
Requires-Python: >=3.7
